<?xml version="1.0"?>
<!--Created by Custom Compiler (TM), build , on Tue Dec  9 19:26:29 2025-->
<file-format version="1.0" name="stateCategory">
 <object type="saModelSetup" version="1" name="models">
  <attribute value="1" type="giBoolean" name="includeGlobal"/>
  <attribute value="/home/nvelazco/workspace28/models/hspice" type="giString" name="includePath"/>
  <collection name="modelFiles">
   <object type="saModelFile" version="1" name="modelFiles">
    <attribute value="1" type="giBoolean" name="enabled"/>
    <attribute value="crn28ull_1d8_elk_v1d8_2p3_shrink0d9_embedded_usage.l" type="giString" name="filename"/>
    <attribute value="TTMacro_MOS_MOSCAP" type="giString" name="section"/>
   </object>
   <object type="saModelFile" version="1" name="modelFiles">
    <attribute value="1" type="giBoolean" name="enabled"/>
    <attribute value="crn28ull_1d8_elk_v1d8_2p3_shrink0d9_embedded_usage.l" type="giString" name="filename"/>
    <attribute value="TT_MOM" type="giString" name="section"/>
   </object>
  </collection>
  <collection name="modelGroupDefs"/>
  <collection name="modelGroups"/>
 </object>
</file-format>
